__init__.py
tweet.py
xclient.py
xtimeline-0.1.0.dist-info/licenses/LICENSE
xtimeline-0.1.0.dist-info/METADATA
xtimeline-0.1.0.dist-info/WHEEL
xtimeline-0.1.0.dist-info/top_level.txt
xtimeline-0.1.0.dist-info/RECORD
