Metadata-Version: 2.4
Name: xtimeline
Version: 0.1.0
Summary: Lightweight X/Twitter timeline client (GraphQL via cURL or auth strategies)
Author: Stephan Akkerman
License: MIT
Keywords: twitter,x,timeline,scraping,aiohttp,asyncio
Requires-Python: >=3.10
License-File: LICENSE
Requires-Dist: aiohttp>=3.12.15
Requires-Dist: uncurl>=0.0.11
Dynamic: license-file
